liquidkit/__main__.py
liquidkit/run.py
liquidkit/__main__/__init__.py
liquidkit-0.0.4.dist-info/METADATA
liquidkit-0.0.4.dist-info/WHEEL
liquidkit-0.0.4.dist-info/top_level.txt
liquidkit-0.0.4.dist-info/RECORD
