Metadata-Version: 2.1
Name: liquidkit
Version: 0.0.4
Summary: Liquid AI API
Author-email: "Liquid AI, Inc" <support@liquid.ai>
Project-URL: Homepage, https://liquid.ai
Keywords: liquidai
Classifier: Development Status :: 4 - Beta
Classifier: Programming Language :: Python
Requires-Python: >=3.6
Requires-Dist: pygame
